martor_markdown_plus/__init__.py
martor_markdown_plus/admin.py
martor_markdown_plus/api.py
martor_markdown_plus/fields.py
martor_markdown_plus/models.py
martor_markdown_plus/settings.py
martor_markdown_plus/urls.py
martor_markdown_plus/utils.py
martor_markdown_plus/views.py
martor_markdown_plus/widgets.py
martor_markdown_plus/extensions/__init__.py
martor_markdown_plus/extensions/del_ins.py
martor_markdown_plus/extensions/emoji.py
martor_markdown_plus/extensions/escape_html.py
martor_markdown_plus/extensions/mdx_video.py
martor_markdown_plus/extensions/mention.py
martor_markdown_plus/extensions/urlize.py
martor_markdown_plus/static/dicts/README.md
martor_markdown_plus/static/dicts/en_US.aff
martor_markdown_plus/static/dicts/en_US.dic
martor_markdown_plus/static/martor/css/_martor-admin.min.css
martor_markdown_plus/static/martor/css/martor-admin.css
martor_markdown_plus/static/martor/css/martor-admin.min.css
martor_markdown_plus/static/martor/css/martor.bootstrap.css
martor_markdown_plus/static/martor/css/martor.bootstrap.min.css
martor_markdown_plus/static/martor/css/martor.semantic.css
martor_markdown_plus/static/martor/css/martor.semantic.min.css
martor_markdown_plus/static/martor/js/_martor.semantic.min.js
martor_markdown_plus/static/martor/js/martor.bootstrap.js
martor_markdown_plus/static/martor/js/martor.bootstrap.min.js
martor_markdown_plus/static/martor/js/martor.semantic.js
martor_markdown_plus/static/plugins/css/ace.min.css
martor_markdown_plus/static/plugins/css/bootstrap.min.css
martor_markdown_plus/static/plugins/css/resizable.min.css
martor_markdown_plus/static/plugins/css/semantic.css
martor_markdown_plus/static/plugins/css/semantic.min.css
martor_markdown_plus/static/plugins/fonts/brand-icons.eot
martor_markdown_plus/static/plugins/fonts/brand-icons.svg
martor_markdown_plus/static/plugins/fonts/brand-icons.ttf
martor_markdown_plus/static/plugins/fonts/brand-icons.woff
martor_markdown_plus/static/plugins/fonts/brand-icons.woff2
martor_markdown_plus-1.2.3.dist-info/METADATA
martor_markdown_plus-1.2.3.dist-info/WHEEL
martor_markdown_plus-1.2.3.dist-info/top_level.txt
martor_markdown_plus-1.2.3.dist-info/RECORD
